HISTORY.md
MANIFEST.in
setup.py
scrapyd_UI.egg-info/PKG-INFO
scrapyd_UI.egg-info/SOURCES.txt
scrapyd_UI.egg-info/dependency_links.txt
scrapyd_UI.egg-info/entry_points.txt
scrapyd_UI.egg-info/not-zip-safe
scrapyd_UI.egg-info/requires.txt
scrapyd_UI.egg-info/top_level.txt
scrapydweb/__init__.py
scrapydweb/__version__.py
scrapydweb/api.py
scrapydweb/cache.py
scrapydweb/default_settings.py
scrapydweb/index.py
scrapydweb/run.py
scrapydweb/utils.py
scrapydweb/vars.py
scrapydweb/directory/__init__.py
scrapydweb/directory/items.py
scrapydweb/directory/log.py
scrapydweb/directory/logs.py
scrapydweb/directory/parse.py
scrapydweb/directory/utils.py
scrapydweb/jobs/__init__.py
scrapydweb/jobs/dashboard.py
scrapydweb/jobs/multinode.py
scrapydweb/jobs/overview.py
scrapydweb/projects/__init__.py
scrapydweb/projects/deploy.py
scrapydweb/projects/manage.py
scrapydweb/projects/schedule.py
scrapydweb/projects/scrapyd_deploy.py
scrapydweb/projects/utils.py
scrapydweb/projects/scrapy/__init__.py
scrapydweb/projects/scrapy/utils/__init__.py
scrapydweb/projects/scrapy/utils/conf.py
scrapydweb/projects/scrapy/utils/python.py
scrapydweb/static/font_804951_mlqq1xmdyc.css
scrapydweb/static/font_804951_pwq5pv3hrpi.css
scrapydweb/static/font_842334_yo81eqsrze.js
scrapydweb/static/github_buttons.html
scrapydweb/static/github_buttons.js
scrapydweb/static/multinode.css
scrapydweb/static/multinode.js
scrapydweb/static/stats.css
scrapydweb/static/style.css
scrapydweb/static/utf8.css
scrapydweb/static/vue.js
scrapydweb/static/common/common.css
scrapydweb/static/common/common.js
scrapydweb/static/common/echarts.min.js
scrapydweb/static/common/jquery.min.js
scrapydweb/static/common/stats.js
scrapydweb/static/element-ui@2.4.6/lib/index.js
scrapydweb/static/element-ui@2.4.6/lib/theme-chalk/index.css
scrapydweb/static/element-ui@2.4.6/lib/theme-chalk/fonts/element-icons.woff
scrapydweb/static/icon/fav.ico
scrapydweb/static/icon/fav.png
scrapydweb/static/icon/spider-man-spiderman-face-mask-round-avatar-512.png
scrapydweb/static/icon/spiderman.png
scrapydweb/static/simpleui/style.css
scrapydweb/static/simpleui/utf8.css
scrapydweb/system/__init__.py
scrapydweb/system/settings.py
scrapydweb/templates/base.html
