Metadata-Version: 1.2
Name: scrapyd-UI
Version: 0.9.9
Summary: Full-featured web UI for Scrapyd cluster management, Scrapy log analysis & visualization
Home-page: https://github.com/my8100/scrapydweb
Author: my8100
Author-email: my8100@gmail.com
License: GNU General Public License v3.0
Platform: UNKNOWN
Classifier: License :: OSI Approved :: GNU General Public License v3 (GPLv3)
Classifier: Programming Language :: Python :: 2.7
Classifier: Programming Language :: Python :: 3.6
Requires-Python: >=2.7, !=3.0.*, !=3.1.*, !=3.2.*, !=3.3.*, !=3.4.*, !=3.5.*
